fustor_fusion/__init__.py
fustor_fusion/cli.py
fustor_fusion/config.py
fustor_fusion/datastore_state_manager.py
fustor_fusion/in_memory_queue.py
fustor_fusion/main.py
fustor_fusion/processing_manager.py
fustor_fusion/queue_integration.py
fustor_fusion/runtime.py
fustor_fusion/runtime_objects.py
fustor_fusion/view.html
fustor_fusion/api/ingestion.py
fustor_fusion/api/session.py
fustor_fusion/api/views.py
fustor_fusion/auth/__init__.py
fustor_fusion/auth/cache.py
fustor_fusion/auth/datastore_cache.py
fustor_fusion/auth/dependencies.py
fustor_fusion/clients/__init__.py
fustor_fusion/core/session_manager.py
fustor_fusion/database/__init__.py
fustor_fusion/jobs/__init__.py
fustor_fusion/jobs/sync_cache.py
fustor_fusion/models/__init__.py
fustor_fusion/models/event.py
fustor_fusion/parsers/__init__.py
fustor_fusion/parsers/background.py
fustor_fusion/parsers/file_directory_parser.py
fustor_fusion/parsers/manager.py
fustor_fusion/parsers/services.py
fustor_fusion-0.2.16.dist-info/METADATA
fustor_fusion-0.2.16.dist-info/WHEEL
fustor_fusion-0.2.16.dist-info/entry_points.txt
fustor_fusion-0.2.16.dist-info/top_level.txt
fustor_fusion-0.2.16.dist-info/RECORD
