Metadata-Version: 2.4
Name: fustor-fusion
Version: 0.2.16
Summary: Fusion service for Fustor
Author-email: Huajin Wang <wanghuajin999@163.com>
Requires-Python: >=3.11
Requires-Dist: fastapi[all]
Requires-Dist: uvicorn
Requires-Dist: sqlalchemy==2.0.41
Requires-Dist: greenlet==3.2.2
Requires-Dist: pydantic>=2.0.0
Requires-Dist: pydantic-settings
Requires-Dist: aiosqlite
Requires-Dist: httpx
Requires-Dist: orjson
Requires-Dist: fustor-common
Requires-Dist: fustor-registry-client
Requires-Dist: fustor-event-model
Provides-Extra: dev
Requires-Dist: pytest>=8.0.0; extra == "dev"
Requires-Dist: ruff>=0.1.0; extra == "dev"
Requires-Dist: mypy>=1.0.0; extra == "dev"
Requires-Dist: pytest-asyncio>=0.23.0; extra == "dev"
